uqtils-0.4.2.dist-info/METADATA
uqtils-0.4.2.dist-info/WHEEL
uqtils-0.4.2.dist-info/entry_points.txt
uqtils-0.4.2.dist-info/licenses/LICENSE
uqtils/__init__.py
uqtils/default.mplstyle
uqtils/example.py
uqtils/gradient.py
uqtils/mcmc.py
uqtils/plots.py
uqtils/sobol.py
uqtils/uq_types.py
uqtils-0.4.2.dist-info/RECORD
