Metadata-Version: 2.1
Name: uqtils
Version: 0.4.2
Summary: Assorted utilities for uncertainty quantification and scientific computing.
Keywords: Uncertainty quantification,Bayesian inference
Author-Email: Joshua Eckels <eckelsjd@umich.edu>
License: GPL-3.0
Classifier: Programming Language :: Python :: 3
Classifier: Operating System :: OS Independent
Classifier: License :: OSI Approved :: GNU General Public License v3 (GPLv3)
Classifier: Topic :: Scientific/Engineering :: Physics
Classifier: Intended Audience :: Science/Research
Project-URL: Repository, https://github.com/eckelsjd/uqtils.git
Project-URL: Documentation, https://eckelsjd.github.io/uqtils/
Requires-Python: >=3.11
Requires-Dist: numpy>=2.0
Requires-Dist: scipy>=1.14
Requires-Dist: tqdm>=4.66
Requires-Dist: h5py>=3.10
Requires-Dist: matplotlib>=3.9.2
